airbrake/__about__.py
airbrake/__init__.py
airbrake/exc.py
airbrake/handler.py
airbrake/notice.py
airbrake/notifier.py
airbrake/utils.py
airbrake-2.2.0.dist-info/LICENSE
airbrake-2.2.0.dist-info/METADATA
airbrake-2.2.0.dist-info/WHEEL
airbrake-2.2.0.dist-info/top_level.txt
airbrake-2.2.0.dist-info/RECORD
