Metadata-Version: 2.1
Name: airbrake
Version: 2.2.0
Summary: Python SDK for airbrake.io
Home-page: https://github.com/airbrake/airbrake-python
Author: BK Box, Sam Stavinoha
Author-email: samuel.stavinoha@rackspace.com
License: Apache License, Version 2.0
Keywords: airbrake exceptions airbrake.io a0cccd45
Platform: UNKNOWN
Classifier: Intended Audience :: Developers
Classifier: License :: OSI Approved :: Apache Software License
Classifier: Operating System :: OS Independent
Classifier: Topic :: Software Development
Classifier: Programming Language :: Python
Classifier: Programming Language :: Python :: 2
Classifier: Programming Language :: Python :: 2.7
Classifier: Programming Language :: Python :: 3
Classifier: Programming Language :: Python :: 3.4
Classifier: Programming Language :: Python :: 3.5
Classifier: Programming Language :: Python :: Implementation :: CPython
Requires-Dist: requests (>=2.20.0)
